phantom_creator/__init__.py
phantom_creator/functions.py
phantom_creator/main.py
phantom_creator/settings.py
phantom_creator/tests/__init__.py
phantom_creator/tests/functions_tests.py
phantom_creator-0.1.0.dist-info/METADATA
phantom_creator-0.1.0.dist-info/WHEEL
phantom_creator-0.1.0.dist-info/top_level.txt
phantom_creator-0.1.0.dist-info/RECORD
