Metadata-Version: 2.1
Name: phantom-creator
Version: 0.1.0
Summary: UNKNOWN
Author: PunchyArchy
Author-email: ksmdrmvscthny@gmail.com
License: UNKNOWN
Platform: UNKNOWN
Requires-Dist: wsqluse (==1.82)
